data/__init__.py
data/datasets.py
data/factories.py
data/parsers.py
data/types.py
data/utils.py
data/graphing/__init__.py
data/graphing/grapher.py
data/graphing/utils.py
data/preprocessing/__init__.py
data/preprocessing/boundary_encoder.py
data/preprocessing/factories.py
data/preprocessing/pipeline.py
data/preprocessing/recursor.py
data/preprocessing/remover.py
data/preprocessing/tensorizers.py
data/preprocessing/tokenizers.py
data/scoring/__init__.py
data/scoring/factories.py
data/scoring/scorers.py
data/scoring/utils.py
inspection/__init__.py
inspection/inspect_files.py
inspection/utils.py
inspection/vocabs.py
models/__init__.py
models/content_ranking/__init__.py
models/content_ranking/content_ranker.py
models/content_ranking/scorer.py
models/content_ranking/utils.py
models/graph_summarization/__init__.py
models/graph_summarization/graph_summarizer.py
models/graph_summarization/section_net.py
models/graph_summarization/sentence_net.py
models/graph_summarization/utils.py
models/graph_summarization/word_net.py
models/submodules/__init__.py
models/submodules/attention.py
models/submodules/encoder.py
models/submodules/ffn.py
models/submodules/fusion.py
models/submodules/section_encoder.py
models/submodules/sentence_encoder.py
models/submodules/utils.py
ourheroes-0.1.data/scripts/ourheroes
training/__init__.py
training/schedulers.py
training/train.py
training/utils.py
training/configuration/__init__.py
training/configuration/config.py
training/configuration/factories.py
training/digesting/__init__.py
training/digesting/app.py
training/digesting/digester.py
training/digesting/factories.py
training/digesting/utils.py
training/eval/__init__.py
training/eval/eval.py
training/eval/evaluator.py
ourheroes-0.1.dist-info/LICENSE
ourheroes-0.1.dist-info/METADATA
ourheroes-0.1.dist-info/WHEEL
ourheroes-0.1.dist-info/top_level.txt
ourheroes-0.1.dist-info/RECORD
