Metadata-Version: 2.1
Name: ourheroes
Version: 0.1
Summary: Project for Deep NLP course.
Home-page: https://github.com/giovannipogg/ourheroes
Author: G. Poggio, G. Calleris
Author-email: s287775@studenti.polito.it
Classifier: Programming Language :: Python :: 3
Classifier: License :: OSI Approved :: MIT License
Classifier: Operating System :: OS Independent
License-File: LICENSE
